safarireadinglist/__init__.py
safarireadinglist/command_line.py
safarireadinglist/export.py
safarireadinglist/reading_list_item.py
safarireadinglist-0.1.1.dist-info/LICENSE
safarireadinglist-0.1.1.dist-info/METADATA
safarireadinglist-0.1.1.dist-info/WHEEL
safarireadinglist-0.1.1.dist-info/entry_points.txt
safarireadinglist-0.1.1.dist-info/top_level.txt
safarireadinglist-0.1.1.dist-info/RECORD
