Metadata-Version: 2.1
Name: safarireadinglist
Version: 0.1.1
Summary: Safari reading list
Home-page: https://github.com/smrfeld/export-safari-reading-list
Author: Oliver K. Ernst
Classifier: Programming Language :: Python :: 3
Classifier: License :: OSI Approved :: MIT License
Classifier: Operating System :: OS Independent
Requires-Python: >=3.6
License-File: LICENSE
Requires-Dist: pandas
